d8s_regexes/__init__.py
d8s_regexes/regexes.py
tests/__init__.py
tests/test_regexes.py
d8s_regexes-0.5.0.dist-info/COPYING
d8s_regexes-0.5.0.dist-info/COPYING.LESSER
d8s_regexes-0.5.0.dist-info/METADATA
d8s_regexes-0.5.0.dist-info/WHEEL
d8s_regexes-0.5.0.dist-info/top_level.txt
d8s_regexes-0.5.0.dist-info/zip-safe
d8s_regexes-0.5.0.dist-info/RECORD
